numina/__init__.py
numina/cli.py
numina/commands/__init__.py
numina/commands/authenticate.py
numina/commands/base.py
numina/commands/counts.py
numina/commands/devices.py
numina/commands/movements.py
numina/commands/utils.py
numina_cli-1.0.1.dist-info/DESCRIPTION.rst
numina_cli-1.0.1.dist-info/METADATA
numina_cli-1.0.1.dist-info/RECORD
numina_cli-1.0.1.dist-info/WHEEL
numina_cli-1.0.1.dist-info/entry_points.txt
numina_cli-1.0.1.dist-info/metadata.json
numina_cli-1.0.1.dist-info/top_level.txt
