Metadata-Version: 2.0
Name: numina-cli
Version: 1.0.1
Summary: A numina command line tool to explore numina sensor data.
Home-page: https://github.com/cty/numina-cli
Author: Rafael Ancheta
Author-email: hello@numina.co
License: Numina
Keywords: cli
Platform: UNKNOWN
Classifier: Intended Audience :: Science/Research
Classifier: Topic :: Utilities
Classifier: License :: Public Domain
Classifier: Natural Language :: English
Classifier: Operating System :: OS Independent
Classifier: Programming Language :: Python :: 2
Classifier: Programming Language :: Python :: 2.6
Classifier: Programming Language :: Python :: 2.7
Classifier: Programming Language :: Python :: 3
Classifier: Programming Language :: Python :: 3.2
Classifier: Programming Language :: Python :: 3.3
Classifier: Programming Language :: Python :: 3.4
Requires-Dist: docopt
Requires-Dist: requests
Provides-Extra: test
Requires-Dist: coverage; extra == 'test'
Requires-Dist: pytest; extra == 'test'
Requires-Dist: pytest-cov; extra == 'test'
